d6tstack/__init__.py
d6tstack/combine_csv.py
d6tstack/convert_xls.py
d6tstack/helpers.py
d6tstack/pyftp_final.py
d6tstack/sniffer.py
d6tstack/sync.py
d6tstack/utils.py
d6tstack-0.2.0.dist-info/LICENSE
d6tstack-0.2.0.dist-info/METADATA
d6tstack-0.2.0.dist-info/WHEEL
d6tstack-0.2.0.dist-info/top_level.txt
d6tstack-0.2.0.dist-info/RECORD
