Metadata-Version: 2.1
Name: d6tstack
Version: 0.2.0
Summary: d6tstack: Quickly ingest CSV and XLS files. Export to pandas, SQL, parquet
Home-page: https://github.com/d6t/d6tstack
Author: DataBolt Team
Author-email: support@databolt.tech
License: MIT
Keywords: d6tstack,ingest csv
Platform: UNKNOWN
Requires-Python: >=3.5
Provides-Extra: psql
Provides-Extra: mysql
Provides-Extra: parquet
Provides-Extra: xls
